tkzs_bd_ads_db_tool-0.2.4.dist-info/licenses/LICENSE
tkzs_bd_db_tool/__init__.py
tkzs_bd_db_tool/datebase.py
tkzs_bd_db_tool/models.py
tkzs_bd_ads_db_tool-0.2.4.dist-info/METADATA
tkzs_bd_ads_db_tool-0.2.4.dist-info/WHEEL
tkzs_bd_ads_db_tool-0.2.4.dist-info/top_level.txt
tkzs_bd_ads_db_tool-0.2.4.dist-info/RECORD
