Metadata-Version: 2.4
Name: tkzs-bd-ads-db-tool
Version: 0.2.4
Summary: 基于sqlalchemy的数据库管理工具
Requires-Python: >=3.11
License-File: LICENSE
Requires-Dist: pymysql>=1.1.1
Requires-Dist: python-dotenv>=1.0.1
Requires-Dist: sqlalchemy>=2.0.39
Dynamic: license-file
